pycognaize/__init__.py
pycognaize/cli.py
pycognaize/clidriver.py
pycognaize/genie.py
pycognaize/index.py
pycognaize/login.py
pycognaize/model.py
pycognaize/common/__init__.py
pycognaize/common/classification_labels.py
pycognaize/common/confidence.py
pycognaize/common/decorators.py
pycognaize/common/enums.py
pycognaize/common/exceptions.py
pycognaize/common/field_collection.py
pycognaize/common/langchain_loader.py
pycognaize/common/lazy_dict.py
pycognaize/common/lazy_group_dict.py
pycognaize/common/numeric_parser.py
pycognaize/common/table_utils.py
pycognaize/common/utils.py
pycognaize/common/white_pixel.jpeg
pycognaize/document/__init__.py
pycognaize/document/document.py
pycognaize/document/html_info.py
pycognaize/document/page.py
pycognaize/document/snapshot.py
pycognaize/document/snapshot_downloader.py
pycognaize/document/field/__init__.py
pycognaize/document/field/area_field.py
pycognaize/document/field/date_field.py
pycognaize/document/field/field.py
pycognaize/document/field/link_field.py
pycognaize/document/field/numeric_field.py
pycognaize/document/field/section_field.py
pycognaize/document/field/span_field.py
pycognaize/document/field/table_field.py
pycognaize/document/field/text_field.py
pycognaize/document/tag/__init__.py
pycognaize/document/tag/cell.py
pycognaize/document/tag/extraction_tag.py
pycognaize/document/tag/html_tag.py
pycognaize/document/tag/section_tag.py
pycognaize/document/tag/span_tag.py
pycognaize/document/tag/table_tag.py
pycognaize/document/tag/tag.py
pycognaize/file_storage/__init__.py
pycognaize/file_storage/path_type_checker.py
pycognaize/file_storage/s3_storage.py
pycognaize/file_storage/storage.py
pycognaize/model_registry/__init__.py
pycognaize/model_registry/login.py
pycognaize/model_registry/submit.py
pycognaize/model_registry/db/__init__.py
pycognaize/model_registry/db/models.py
pycognaize-1.4.57.dist-info/licenses/LICENSE.txt
pycognaize-1.4.57.dist-info/METADATA
pycognaize-1.4.57.dist-info/WHEEL
pycognaize-1.4.57.dist-info/entry_points.txt
pycognaize-1.4.57.dist-info/top_level.txt
pycognaize-1.4.57.dist-info/RECORD
