Metadata-Version: 2.4
Name: pycognaize
Version: 1.4.57
Home-page: https://github.com/cognaize/pycognaize
Author: Cognaize
License: Apache License 2.0
Project-URL: Source, https://github.com/cognaize/pycognaize
Project-URL: Reference, https://pycognaize.readthedocs.io/en/latest/
Project-URL: Changelog, https://github.com/cognaize/pycognaize/blob/master/CHANGELOG.md
Requires-Python: >= 3.9
License-File: LICENSE.txt
Requires-Dist: pandas
Requires-Dist: numpy
Requires-Dist: pymongo
Requires-Dist: requests
Requires-Dist: simplejson
Requires-Dist: pillow
Requires-Dist: pymupdf
Requires-Dist: urllib3
Requires-Dist: lxml
Requires-Dist: beautifulsoup4
Requires-Dist: dataclasses; python_version <= "3.6"
Requires-Dist: PyYAML
Requires-Dist: click
Requires-Dist: anytree
Requires-Dist: tabulate
Requires-Dist: cloudpathlib[azure,gs,s3]~=0.18
Requires-Dist: pyarrow
Dynamic: license
Dynamic: license-file
Dynamic: project-url
Dynamic: requires-python
